get_abtest/__init__.py
get_abtest/__version__.py
get_abtest/get_abtest.py
get_abtest-0.1.1.dist-info/METADATA
get_abtest-0.1.1.dist-info/WHEEL
get_abtest-0.1.1.dist-info/top_level.txt
get_abtest-0.1.1.dist-info/RECORD
