Metadata-Version: 2.1
Name: get-abtest
Version: 0.1.1
Summary: My short description for my project.
Home-page: https://github.com/me/myproject
Author: Xianglu He
Author-email: xlhe@ucdavis.edu
License: MIT
Platform: UNKNOWN
Classifier: License :: OSI Approved :: MIT License
Classifier: Programming Language :: Python
Classifier: Programming Language :: Python :: 3
Classifier: Programming Language :: Python :: 3.6
Classifier: Programming Language :: Python :: Implementation :: CPython
Classifier: Programming Language :: Python :: Implementation :: PyPy
Requires-Python: >=3.6.0
